markdownmail/__init__.py
markdownmail/test_markdownmail.py
markdownmail/styles/__init__.py
markdownmail/styles/default.css
markdownmail-0.11.1.dist-info/LICENCE
markdownmail-0.11.1.dist-info/METADATA
markdownmail-0.11.1.dist-info/WHEEL
markdownmail-0.11.1.dist-info/top_level.txt
markdownmail-0.11.1.dist-info/zip-safe
markdownmail-0.11.1.dist-info/RECORD
