Metadata-Version: 2.1
Name: markdownmail
Version: 0.11.1
Summary: E-mail with text and html content provided with markdown
Home-page: https://gitlab.com/yaal/markdownmail
Author: Yaal Team
Author-email: contact@yaal.coop
License: MIT
Keywords: mail markdown yaal
Classifier: Programming Language :: Python
Classifier: Development Status :: 5 - Production/Stable
Classifier: Intended Audience :: Developers
Classifier: License :: OSI Approved :: MIT License
Classifier: Operating System :: OS Independent
Classifier: Topic :: Software Development :: Libraries :: Python Modules
Classifier: Programming Language :: Python :: 2.7
Classifier: Programming Language :: Python :: 3
License-File: LICENCE
Requires-Dist: Markdown==3.*
Requires-Dist: Envelopes==0.4
